README.md
setup.py
src/timewarp/__init__.py
src/timewarp/timewarp.py
src/timewarp.egg-info/PKG-INFO
src/timewarp.egg-info/SOURCES.txt
src/timewarp.egg-info/dependency_links.txt
src/timewarp.egg-info/entry_points.txt
src/timewarp.egg-info/requires.txt
src/timewarp.egg-info/top_level.txt