Metadata-Version: 2.1
Name: timewarp
Version: 0.0.3
Summary: datetime wrapper that allows you to specify datetimes using a succinct shorthand.
Home-page: https://github.com/conor-f/timewarp
License: UNKNOWN
Platform: UNKNOWN
Requires-Python: >=3.6
